README.txt
setup.py
example_pkg_pyzwave/__init__.py
example_pkg_pyzwave/example_pkg_pyzwave.py
example_pkg_pyzwave.egg-info/PKG-INFO
example_pkg_pyzwave.egg-info/SOURCES.txt
example_pkg_pyzwave.egg-info/dependency_links.txt
example_pkg_pyzwave.egg-info/top_level.txt
example_pkg_pyzwave.egg-info/zip-safe